{
  "id": "mcas-new-compliance-facilitation-scheme-2026-a-golden-window-to-clean-up-your-books-and-save-big-1772541257796",
  "title": "MCA's New Compliance Facilitation Scheme, 2026: A Golden Window to Clean Up Your Books (and Save Big!)",
  "slug": "mcas-new-compliance-facilitation-scheme-2026-a-golden-window-to-clean-up-your-books-and-save-big",
  "date": "3 March 2026",
  "content": "# MCA's New Compliance Facilitation Scheme, 2026: A Golden Window to Clean Up Your Books (and Save Big!)\n\nEver felt the weight of those piled-up ROC filings, with additional fees mounting day by day, almost feeling like an endless cycle? Many companies, especially our diligent MSMEs and new-age startups, find themselves in this very predicament. The sheer burden of accumulated penalties for delayed filings can often be a significant roadblock, making compliance feel like an uphill battle. But chinta not, my corporate friends! The Ministry of Corporate Affairs (MCA) has once again stepped in with a much-needed relief measure, a true \"compliance reset\" – the **Companies Compliance Facilitation Scheme, 2026 (CCFS-2026)**.\n\nIntroduced via **General Circular No. 01/2026 dated February 24, 2026**, this scheme is a one-time opportunity, a golden window, if you will, to regularize your pending statutory filings at significantly reduced penalties. The scheme is not just about fee reduction; it's a clear signal from the government towards promoting ease of doing business and ensuring a cleaner, more accurate corporate registry. Let's dive deep into what this means for you and your company.\n\n## Why This Scheme Now? The Genesis of Relief\n\nUnder the Companies Act, 2013, the filing of Annual Returns (Form MGT-7/MGT-7A) and Financial Statements (Form AOC-4 and its variants) is a mandatory annual ritual. Miss the deadline, and the penalty meter starts ticking – a hefty additional fee of **₹100 per day of delay**, without any upper limit, since July 1, 2018. Imagine the cumulative burden on a company with several years of pending compliances! This often translates into lakhs of rupees, making it difficult for many, especially smaller entities, to get back on track.\n\nRecognizing these genuine challenges and acting on representations from various stakeholders, the Central Government, exercising its powers under **Sections 460 read with Section 403 of the Companies Act, 2013**, has introduced CCFS-2026. The objective is multi-fold: to improve overall compliance levels, ensure the MCA-21 registry reflects updated and accurate information, and provide a cost-effective pathway for inactive or defunct entities to either gain dormant status or exit the registry gracefully.\n\n## Unpacking the Companies Compliance Facilitation Scheme, 2026\n\nThe CCFS-2026 is a time-bound scheme, operational from **April 15, 2026, to July 15, 2026**. This three-month window is your chance to correct past non-compliances without the looming threat of exorbitant penalties. So, what are the key benefits being offered?\n\n### 1. Drastic Reduction in Additional Fees for Delayed Filings\n\nThis is perhaps the biggest draw for most companies. If you have pending Annual Returns or Financial Statements (or other specified e-forms), you can now file them by paying the normal filing fees along with **only 10% of the additional fees** that would otherwise be payable for the delay. That's a whopping **90% waiver** on the additional fee component! Think about it, for a delay that might have cost you lakhs, you now pay a fraction. *Bahut relief ki baat hai, isn't it?*\n\n**Applicable Forms (Illustrative):** The scheme covers a wide array of forms under both the Companies Act, 2013, and the erstwhile Companies Act, 1956. These primarily include:\n*   **Companies Act, 2013:** MGT-7 (Annual Return), MGT-7A (Abridged Annual Return for OPCs and Small Companies), AOC-4 (Financial Statements), AOC-4 CFS (Consolidated Financial Statements), AOC-4 XBRL, ADT-1 (Appointment of Auditor), FC-3 (Annual Accounts of Foreign Company), FC-4 (Annual Return of Foreign Company).\n*   **Companies Act, 1956:** Forms like 20B, 21A, 23AC, 23ACA, 66, 23B, and their XBRL variants.\n\n### 2. Concessional Rates for Obtaining Dormant Company Status\n\nFor companies that are inactive but wish to remain on the corporate registry with minimal compliance requirements, the scheme offers a simplified path to obtaining **\"Dormant Company\" status** under Section 455 of the Act. By filing **e-form MSC-1**, these companies will only have to pay **50% of the normal filing fee**. This is a great opportunity to reduce ongoing compliance burdens without completely dissolving the entity.\n\n### 3. Reduced Fees for Voluntary Strike-Off\n\nSometimes, a company has served its purpose or simply become defunct. For such entities, the CCFS-2026 provides an economical exit route. Companies can apply for **striking off their name from the Register of Companies** by filing **e-form STK-2** and paying **only 25% of the applicable filing fees**. This significantly reduces the financial barrier to a clean closure.\n\n### 4. Immunity from Penal Proceedings\n\nBeyond the fee reductions, the scheme also offers crucial immunity.\n*   **For defaults under Section 92 (Annual Return) and Section 137 (Financial Statements):** No penalty shall be levied if the filings are completed under the scheme either *before* the issuance of a notice by the adjudicating officer, or *within 30 days* of the issuance of such notice.\n*   **For other specified forms (like ADT-1, FC-3, FC-4, and legacy forms):** Immunity from *prospective* penal action is available, provided no prosecution or adjudication proceedings have been initiated against the company before the filing under this scheme.\n\nThis immunity provision is critical, offering a fresh start to companies that have been grappling with the fear of extensive legal action.\n\n## Who Cannot Avail This Scheme? (The Exclusions)\n\nWhile the scheme is broad, it's not a blanket amnesty. Certain categories of companies are **not eligible** for CCFS-2026:\n*   Companies against which a **final notice for striking off** under Section 248 of the Act has already been initiated by the Registrar.\n*   Companies that have already **applied for voluntary strike-off** or **dormant status** prior to the commencement of this scheme.\n*   Companies that have been **dissolved pursuant to a scheme of amalgamation**.\n*   **Vanishing companies**.\n\nThese exclusions ensure that the scheme is truly for genuine defaulters seeking to regularize, rather than for entities already deep into the process of being removed from the registry or those with a questionable compliance history.\n\n## What Happens After July 15, 2026? A Word of Caution!\n\nThe MCA has made it abundantly clear: this is a **one-time opportunity**. Companies should not expect another such window to open soon. Once the scheme closes on **July 15, 2026**, the Registrars of Companies (RoCs) are expected to take **strict necessary regulatory actions** against all companies that fail to avail the benefits of the scheme and continue to remain non-compliant. This could lead to significant financial penalties, strike-off proceedings, and even disqualification of directors. *So, yeh mauka hath se jaane mat dena!*\n\n## Conclusion: Seize the Opportunity!\n\nThe Companies Compliance Facilitation Scheme, 2026, is a thoughtful and pragmatic move by the MCA. It acknowledges the challenges faced by businesses and provides a realistic pathway to rectify past non-compliances without excessive financial strain. For defaulting companies, this is an unparalleled chance to clean up their records, ensure compliance, and safeguard their directors from potential disqualification.\n\nAs a professional, my advice would be to immediately undertake a comprehensive review of your company's compliance status. Identify all pending filings, calculate the revised fees under the scheme, and make a plan to complete all necessary submissions well before the **July 15, 2026 deadline**. Don't wait until the last minute to avoid technical glitches or unforeseen issues. This scheme is a clear signal from the government – get compliant now, or face the full force of the law later. *Chalo, ab der kis baat ki? Let's get compliant!*\n\n## Read the Official Document\n* [Download the Official Notification/Circular here](https://mca.gov.in/bin/dms/getdocument?doc=MTU=&pid=MTAzOTY3MTMxMjE1MTEyMDA0NDQ0NDQ=&ct=Q3JjbCBJc3N1ZWQgYnkgQ3JwIEhlYWQ=)\n\n*Published on: 3 March 2026*",
  "type": "blog"
}