{
  "id": "union-budget-2026-navigating-the-7-pillars-of-income-tax-transformation-effective-april-1-2026-1773405311540",
  "title": "Union Budget 2026: Navigating the 7 Pillars of Income Tax Transformation Effective April 1, 2026",
  "slug": "union-budget-2026-navigating-the-7-pillars-of-income-tax-transformation-effective-april-1-2026",
  "date": "13 March 2026",
  "content": "# Union Budget 2026: Navigating the 7 Pillars of Income Tax Transformation Effective April 1, 2026\n\nNamaste, colleagues! The Union Budget 2026 has just been unveiled, and as expected, it brings a fresh wave of significant income tax changes that are set to redefine our compliance and advisory strategies. These aren't just minor tweaks; we're looking at foundational shifts, with many provisions kicking in from April 1, 2026. It's time to roll up our sleeves and understand the nuances, because, as we all know, knowledge is power, especially in our profession.\n\nLet’s delve deeper into the seven most impactful changes that demand our immediate attention.\n\n## 1. The Dawn of the New Income Tax Act, 2025\n\nPerhaps the most monumental change this Budget introduces is the formal announcement that the **New Income Tax Act, 2025, will come into effect from April 1, 2026**. This isn't just a renumbering exercise; it's a comprehensive overhaul aimed at simplifying the existing labyrinthine tax laws, which have grown considerably since the Income-tax Act, 1961. The intent is to reduce complexity, enhance clarity, and improve ease of compliance for all stakeholders.\n\nThis new legislation reorganises provisions related to return processing, scrutiny assessments, and reassessment of escaped income, simplifying the drafting while largely retaining existing procedures. We can anticipate a simpler framework, which, frankly, is a welcome move for all of us grappling with the current complexities. Simplified Income Tax Rules and Forms are also expected to be notified shortly, redesigned for easier compliance.\n\n## 2. Rationalized Individual Income Tax Slabs Under the New Tax Regime\n\nFor individual taxpayers, especially those embracing the new tax regime, the Budget brings further rationalization to the income tax slabs for **FY 2025-26 (AY 2026-27)**. While the old tax regime largely remains untouched, the government continues its push to make the new regime more attractive and the default option.\n\nHere’s a quick look at the revised slab structure under the new regime:\n\n| Income Bracket (INR) | Old New Regime Rate (FY 2024-25) | New New Regime Rate (FY 2025-26 / AY 2026-27) |\n| :------------------- | :------------------------------- | :-------------------------------------------- |\n| Up to 4,00,000       | Nil                              | Nil                                           |\n| 4,00,001 to 8,00,000 | 5%                               | 5%                                            |\n| 8,00,001 to 12,00,000| 10%                              | 10%                                           |\n| 12,00,001 to 16,00,000| 15%                             | 15%                                           |\n| 16,00,001 to 20,00,000| 20%                             | 20%                                           |\n| 20,00,001 to 24,00,000| Not applicable                   | 25%                                           |\n| Above 24,00,000      | 30%                              | 30%                                           |\n\n_Note: This table reflects the updated understanding of slabs based on Budget 2026 announcements for AY 2026-27._\n\nWith the enhanced **Section 87A rebate** (increased in Budget 2025 from Rs. 25,000 to Rs. 60,000 and continuing in Budget 2026) and a standard deduction of **Rs. 75,000 for salaried individuals**, income up to **Rs. 12.75 lakh** can effectively become tax-free under the revised structure for resident individuals. This is a significant move to boost disposable income, especially for our middle and upper-middle-income taxpayers.\n\n## 3. Streamlined Tax Collected at Source (TCS) on Foreign Remittances\n\nThe Budget has brought some relief and rationalization to **TCS provisions, particularly concerning overseas remittances**. We saw considerable discussion around this in the previous year, and the government has responded by easing the rates.\n\n| Scenario                      | Old TCS Rate                  | New TCS Rate (Effective April 1, 2026) |\n| :---------------------------- | :---------------------------- | :--------------------------------------------- |\n| Overseas Tour Package         | 5% or 20% (depending on amount)| 2% (without any stipulation of amount)         |\n| Education/Medical Treatment (LRS)| 5%                           | 2%                                             |\n\nThis reduction aims to simplify compliance and alleviate the immediate cash outflow for individuals and families undertaking foreign travel or remitting funds for essential purposes like education and medical care.\n\n## 4. Revised Minimum Alternate Tax (MAT) Regime\n\nFor our corporate clients, particularly those under the old tax regime, the **Minimum Alternate Tax (MAT)** provisions have seen notable changes. The government's objective is to encourage companies to shift to the new, lower corporate tax regimes while also refining the MAT framework.\n\nThe MAT rate has been **reduced from 15% to 14%**. More significantly, from April 1, 2026, MAT will be treated as the **final rate of tax** for companies opting for the old tax regime, and there will be **no further accumulation of MAT credit**. However, existing accumulated MAT credit (till March 31, 2026) can still be utilized, but with restrictions: it will be allowed in the new tax regime only to the extent of **25% of the tax liability** for domestic companies, and up to the difference between normal tax liability and MAT for foreign companies. This is a crucial point; clients with substantial MAT credits need to re-strategize their tax planning.\n\n## 5. Expanded Scope for Filing Updated Returns\n\nIn a move aimed at **reducing litigation and promoting voluntary compliance**, the government has further expanded the scope of filing updated returns. This facility, previously introduced, now offers even greater flexibility.\n\n| Old Provision                                                                                                                                              | New Provision (Effective April 1, 2026)                                                                                                                                      |\n| :--------------------------------------------------------------------------------------------------------------------------------------------------------- | :------------------------------------------------------------------------------------------------------------------------------------------------------------------------------------------ |\n| Updated returns could not be filed to reduce losses or after the issuance of a reassessment notice.                                                        | Taxpayers can now file an **updated return** even for the purpose of **reducing the loss** originally declared. This allows for correction of over-reported losses.                              |\n|                                                                                                                                                            | An updated return can also be filed **even after the receipt of a reassessment notice**, provided it is filed within the time specified in such notice.                                      |\n|                                                                                                                                                            | In cases where an updated return is filed after the issuance of a reassessment notice, an **additional 10% tax** will be levied over and above the existing additional tax.      |\n\nThis is a welcome relief for taxpayers who might have genuinely missed something or need to correct an over-reported loss. However, the additional tax component for post-notice filing is something one must factor in.\n\n## 6. Restriction on Deduction for Interest Against Dividend Income\n\nHere’s a change that will impact investors, especially those leveraging borrowed funds for equity investments. The Budget proposes to **disallow any deduction for interest expenditure incurred for earning dividend income or income from units of mutual funds.**\n\n| Old Provision                                                                                                 | New Provision (Effective April 1, 2026)                                                                                                                                                                            |\n| :-------------------------------------------------------------------------------------------------------------------------- | :----------------------------------------------------------------------------------------------------------------------------------------------------------------------------------------------------------------------- |\n| Section 93(2) of the Income-tax Act, 2025 (corresponding to Section 57 of the 1961 Act) permitted deduction of interest expenditure against dividend income, restricted to 20% of such dividend income. | **No deduction**, including interest, shall be allowed in respect of dividend income or income from units of mutual funds or specified UTI units. This removes the 20% interest deduction limit altogether. |\n\nThis move aims to prevent artificial erosion of taxable income through interest claims against what is often passive income. Investors will need to re-evaluate their financing structures for dividend-yielding investments.\n\n## 7. Reduction in Tax Rate on Unexplained Income\n\nThe Budget has introduced a significant change in the taxation of **unexplained income**, often referred to as 'black money'. While the intent to curb such income remains strong, there's a rationalization in the penal tax rates.\n\n| Old Provision                                                                                                                                  | New Provision (Effective April 1, 2026)                                                                                                                                                                                                                                                                   |\n| :-------------------------------------------------------------------------------------------------------------------------------------------------------------- | :------------------------------------------------------------------------------------------------------------------------------------------------------------------------------------------------------------------------------------------------------------------------------------------------------------------------- |\n| Section 195 of the Income-tax Act, 2025 (corresponding to Section 115BBE of the 1961 Act) taxed unexplained income at 60%, leading to an effective rate of 78% (including surcharge and cess). A separate penalty of 10% was also levied under Section 443. | The tax rate under **Section 195 has been reduced to 30%**. This effectively brings down the total tax rate (after surcharge and cess) to 39%. |\n|                                                                                                                                                                 | Furthermore, **Section 443, which levied a separate 10% penalty, is proposed to be omitted.** Penalty for such income will now be governed by the framework for under-reporting in consequence of misreporting under Section 439(11) of the 2025 Act (corresponding to Section 270A(9) of the 1961 Act).                 |\n\nThis rationalization might seem counter-intuitive, but the government's aim appears to be encouraging disclosure by making the penalty less prohibitive, thereby broadening the tax base rather than just penalizing it heavily.\n\n## Final Thoughts: Adapt and Strategize\n\nWell, there you have it – a quick rundown of the major income tax changes from Union Budget 2026. The implementation of the New Income Tax Act, 2025, from April 1, 2026, sets the stage for a new era of tax administration. While individual taxpayers under the new regime get some relief, and compliance for certain transactions is eased, other areas like dividend income deductions demand careful re-planning.\n\nFor us, the tax professionals, yeh bahut important hai to stay abreast of these changes. We must proactively advise our clients on how these amendments will impact their financial planning for **FY 2026-27 onwards**. The emphasis is clearly on simplification, expanding the tax base, and reducing litigation, and we need to help our clients align with this vision.\n\n## Read the Official Document\n* [Download the Official Notification/Circular here](https://www.indiabudget.gov.in/budget_documents/finance_bill.php)\n* [Explore Union Budget Documents 2026-2027](https://www.indiabudget.gov.in/budget_documents/index.php)\n* [Visit the Ministry of Finance Website](https://finmin.nic.in/)\n\n*Published on: 13 March 2026*",
  "type": "blog"
}