{
  "id": "cbdt-releases-draft-income-tax-rules-forms-2026-for-public-feedback-1770686545584",
  "title": "CBDT Releases Draft Income Tax Rules & Forms, 2026 for Public Feedback",
  "slug": "cbdt-releases-draft-income-tax-rules-forms-2026-for-public-feedback",
  "date": "10 February 2026",
  "content": "# CBDT Releases Draft Income Tax Rules & Forms, 2026 for Public Feedback\n\nEk important update hai! The Central Board of Direct Taxes (CBDT) ne Draft Income-tax Rules, 2026 aur Forms ko public consultation ke liye announce kiya hai. Ye new rules, Income-tax Act, 2025 ke saath, April 1, 2026 se effective honge.\n\nYahan kuch key details hain:\n\n*   **Purpose:** These draft rules and forms aim to simplify tax compliance, reduce litigation, and ease the compliance burden, replacing the existing Income-tax Rules, 1962.\n*   **Consultation Period:** Stakeholders aur general public 22 February, 2026 tak apne comments aur suggestions submit kar sakte hain.\n*   **Key Changes:** The number of rules has been significantly reduced from 511 to 333, and forms from 399 to 190, making the process more streamlined.\n*   **Feedback Categories:** Inputs are specifically invited on four broad areas: simplification of language, reduction of litigation, reduction of compliance burden, and identification of redundant or obsolete rules and forms.\n*   **Submission Mechanism:** Comments can be submitted through a dedicated utility launched on the e-filing portal (eportal.incometax.gov.in), which has been live since February 4, 2026.\n\n## Read the Official Document\n*   [Download the Official Notification/Circular here](https://www.incometax.gov.in/iec/foportal/latest-news)\n\n*Published on: 10 February 2026*",
  "type": "update"
}