{
  "id": "income-tax-exemption-for-kota-development-authority-us-1046a-notified-by-cbdt-1767920406466",
  "title": "Income Tax Exemption for Kota Development Authority u/s 10(46A) Notified by CBDT!",
  "slug": "income-tax-exemption-for-kota-development-authority-us-1046a-notified-by-cbdt",
  "date": "9 January 2026",
  "content": "# Income Tax Exemption for Kota Development Authority u/s 10(46A) Notified by CBDT!\n\nEk important update hai. Government ne Kota Development Authority ke liye income tax exemption announce kiya hai under Section 10(46A) of the Income-tax Act, 1961.\n\n*   **What's New:** Central Government ne Kota Development Authority (KDA) ko Income-tax Act, 1961 ke Section 10(46A) ke तहत income tax exemption ke liye notify kiya hai.\n*   **Notification Details:** Yeh exemption Notification No. 04/2026 – Income Tax, dated January 7, 2026, ke through notify kiya gaya hai.\n*   **Authority:** Kota Development Authority ko Kota Development Authority Act, 2023 (Act No. 31 of 2023) ke under constitute kiya gaya hai.\n*   **Effective From:** Yeh exemption Assessment Year 2025-26 se effective hoga.\n*   **Key Condition:** Exemption tab tak applicable rahega jab tak KDA Kota Development Authority Act, 2023 ke under function karta rahega aur Section 10(46A) ke specified statutory purposes ko carry out karega.\n\n## Read the Official Document\n*   [Download the Official Notification/Circular here](https://www.incometax.gov.in/iec/foportal/latest-news/notifications)\n\n*Published on: 9 January 2026*",
  "type": "update"
}